mass_demo/__init__.py
mass_demo/settings.py
mass_demo/urls.py
mass_demo/wsgi.py
massadmin/INSTALL
massadmin/LICENSE
massadmin/__init__.py
massadmin/apps.py
massadmin/massadmin.py
massadmin/settings.py
massadmin/urls.py
massadmin/locale/ca/LC_MESSAGES/django.mo
massadmin/locale/ca/LC_MESSAGES/django.po
massadmin/locale/cs/LC_MESSAGES/django.mo
massadmin/locale/cs/LC_MESSAGES/django.po
massadmin/locale/es/LC_MESSAGES/django.mo
massadmin/locale/es/LC_MESSAGES/django.po
massadmin/locale/nl/LC_MESSAGES/django.mo
massadmin/locale/nl/LC_MESSAGES/django.po
massadmin/locale/pl/LC_MESSAGES/django.mo
massadmin/locale/pl/LC_MESSAGES/django.po
massadmin/locale/pt/LC_MESSAGES/django.mo
massadmin/locale/pt/LC_MESSAGES/django.po
massadmin/locale/ru/LC_MESSAGES/django.mo
massadmin/locale/ru/LC_MESSAGES/django.po
massadmin/locale/zh_cn/LC_MESSAGES/django.mo
massadmin/locale/zh_cn/LC_MESSAGES/django.po
massadmin/locale/zh_hans/LC_MESSAGES/django.mo
massadmin/locale/zh_hans/LC_MESSAGES/django.po
massadmin/templates/admin/mass_change_form.html
massadmin/templates/admin/save_only_submit_line.html
massadmin/templates/admin/includes/mass_fieldset.html
massadmin/templatetags/__init__.py
massadmin/templatetags/truncchar.py
tests/__init__.py
tests/admin.py
tests/mocks.py
tests/models.py
tests/settings.py
tests/site.py
tests/tests.py
tests/urls.py
tests/urls_custom_admin.py
tests/migrations/0001_initial.py
tests/migrations/0002_auto_20211217_0041.py
tests/migrations/__init__.py
django_mass_edit-3.5.0.dist-info/METADATA
django_mass_edit-3.5.0.dist-info/WHEEL
django_mass_edit-3.5.0.dist-info/top_level.txt
django_mass_edit-3.5.0.dist-info/RECORD
