Metadata-Version: 2.1
Name: django-mass-edit
Version: 3.5.0
Summary: Make bulk changes in the Django admin interface
Home-page: https://github.com/burke-software/django-mass-edit
Author: David Burke
Author-email: david@burkesoftware.com
License: BSD
Keywords: django admin
Classifier: Development Status :: 5 - Production/Stable
Classifier: Environment :: Web Environment
Classifier: Framework :: Django
Classifier: Programming Language :: Python
Classifier: Programming Language :: Python :: 2.7
Classifier: Programming Language :: Python :: 3.6
Classifier: Intended Audience :: Developers
Classifier: Intended Audience :: System Administrators
Classifier: License :: OSI Approved :: BSD License
Requires-Dist: django
